bedrockprotopy/__init__.py
bedrockprotopy/login.py
bedrockprotopy/ping.py
bedrockprotopy/send.py
bedrockprotopy/test_server.py
bedrockprotopy-0.0.3.dist-info/licenses/LICENSE
bedrockprotopy-0.0.3.dist-info/METADATA
bedrockprotopy-0.0.3.dist-info/WHEEL
bedrockprotopy-0.0.3.dist-info/top_level.txt
bedrockprotopy-0.0.3.dist-info/RECORD
