Metadata-Version: 2.4
Name: bedrockprotopy
Version: 0.0.3
Summary: Minecraft bedrock edition protocol library written in python
Home-page: https://github.com/elitrycraft/bedrockprotopy
Author: Deniz1111212(elitrycraft)
Author-email: elitrycraft@outlook.com
License: MIT
Classifier: Programming Language :: Python :: 3.11
Classifier: License :: OSI Approved :: MIT License
Classifier: Operating System :: OS Independent
Requires-Python: >=3.7
License-File: LICENSE
Dynamic: author
Dynamic: author-email
Dynamic: classifier
Dynamic: description
Dynamic: description-content-type
Dynamic: home-page
Dynamic: license
Dynamic: license-file
Dynamic: requires-python
Dynamic: summary
